stored_variable/__init__.py
stored_variable-1.dist-info/DESCRIPTION.rst
stored_variable-1.dist-info/METADATA
stored_variable-1.dist-info/RECORD
stored_variable-1.dist-info/WHEEL
stored_variable-1.dist-info/metadata.json
stored_variable-1.dist-info/top_level.txt
