Metadata-Version: 2.0
Name: stored-variable
Version: 1
Summary: It creates stored variable
Home-page: UNKNOWN
Author: Saksham Jain
Author-email: UNKNOWN
License: UNKNOWN
Platform: UNKNOWN
